llmcode/__init__.py
llmcode/__main__.py
llmcode/_version.py
llmcode/analytics.py
llmcode/args.py
llmcode/args_formatter.py
llmcode/commands.py
llmcode/copypaste.py
llmcode/diffs.py
llmcode/dump.py
llmcode/editor.py
llmcode/exceptions.py
llmcode/format_settings.py
llmcode/gui.py
llmcode/help.py
llmcode/help_pats.py
llmcode/history.py
llmcode/io.py
llmcode/linter.py
llmcode/llm.py
llmcode/main.py
llmcode/mdstream.py
llmcode/models.py
llmcode/prompts.py
llmcode/repo.py
llmcode/repomap.py
llmcode/report.py
llmcode/run_cmd.py
llmcode/scrape.py
llmcode/sendchat.py
llmcode/special.py
llmcode/urls.py
llmcode/utils.py
llmcode/versioncheck.py
llmcode/voice.py
llmcode/watch.py
llmcode/watch_prompts.py
llmcode/coders/__init__.py
llmcode/coders/architect_coder.py
llmcode/coders/architect_prompts.py
llmcode/coders/ask_coder.py
llmcode/coders/ask_prompts.py
llmcode/coders/base_coder.py
llmcode/coders/base_prompts.py
llmcode/coders/chat_chunks.py
llmcode/coders/editblock_coder.py
llmcode/coders/editblock_fenced_coder.py
llmcode/coders/editblock_fenced_prompts.py
llmcode/coders/editblock_func_coder.py
llmcode/coders/editblock_func_prompts.py
llmcode/coders/editblock_prompts.py
llmcode/coders/editor_editblock_coder.py
llmcode/coders/editor_editblock_prompts.py
llmcode/coders/editor_whole_coder.py
llmcode/coders/editor_whole_prompts.py
llmcode/coders/help_coder.py
llmcode/coders/help_prompts.py
llmcode/coders/search_replace.py
llmcode/coders/single_wholefile_func_coder.py
llmcode/coders/single_wholefile_func_prompts.py
llmcode/coders/udiff_coder.py
llmcode/coders/udiff_prompts.py
llmcode/coders/wholefile_coder.py
llmcode/coders/wholefile_func_coder.py
llmcode/coders/wholefile_func_prompts.py
llmcode/coders/wholefile_prompts.py
llmcode/queries/README.md
llmcode/queries/tree-sitter-c-tags.scm
llmcode/queries/tree-sitter-c_sharp-tags.scm
llmcode/queries/tree-sitter-cpp-tags.scm
llmcode/queries/tree-sitter-dart-tags.scm
llmcode/queries/tree-sitter-elisp-tags.scm
llmcode_chat-0.1.1.dist-info/LICENSE.txt
llmcode_chat-0.1.1.dist-info/METADATA
llmcode_chat-0.1.1.dist-info/WHEEL
llmcode_chat-0.1.1.dist-info/entry_points.txt
llmcode_chat-0.1.1.dist-info/top_level.txt
llmcode_chat-0.1.1.dist-info/RECORD
